LICENSE
MANIFEST.in
README.rst
setup.py
django_yaccounts.egg-info/PKG-INFO
django_yaccounts.egg-info/SOURCES.txt
django_yaccounts.egg-info/dependency_links.txt
django_yaccounts.egg-info/requires.txt
django_yaccounts.egg-info/top_level.txt
yaccounts/__init__.py
yaccounts/admin.py
yaccounts/backends.py
yaccounts/exceptions.py
yaccounts/forms.py
yaccounts/models.py
yaccounts/urls.py
yaccounts/utils.py
yaccounts/views.py
yaccounts/views_facebook.py
yaccounts/views_twitter.py
yaccounts/api/__init__.py
yaccounts/api/__init__.pyc
yaccounts/api/handlers.py
yaccounts/api/handlers.pyc
yaccounts/api/serializers.py
yaccounts/api/serializers.pyc
yaccounts/api/urls.py
yaccounts/api/urls.pyc
yaccounts/locale/pt_PT/LC_MESSAGES/django.mo
yaccounts/locale/pt_PT/LC_MESSAGES/django.po
yaccounts/static/.DS_Store
yaccounts/static/yaccounts/.DS_Store
yaccounts/static/yaccounts/css/style.css
yaccounts/static/yaccounts/images/.DS_Store
yaccounts/static/yaccounts/images/avatar_default.png
yaccounts/static/yaccounts/images/gray-140x140.png
yaccounts/static/yaccounts/js/api_keys.js
yaccounts/static/yaccounts/libs/.DS_Store
yaccounts/static/yaccounts/libs/jquery-1.10.2.min.js
yaccounts/static/yaccounts/libs/bootstrap-3.0.3/.DS_Store
yaccounts/static/yaccounts/libs/bootstrap-3.0.3/css/bootstrap-theme.css
yaccounts/static/yaccounts/libs/bootstrap-3.0.3/css/bootstrap-theme.min.css
yaccounts/static/yaccounts/libs/bootstrap-3.0.3/css/bootstrap.css
yaccounts/static/yaccounts/libs/bootstrap-3.0.3/css/bootstrap.min.css
yaccounts/static/yaccounts/libs/bootstrap-3.0.3/fonts/glyphicons-halflings-regular.eot
yaccounts/static/yaccounts/libs/bootstrap-3.0.3/fonts/glyphicons-halflings-regular.svg
yaccounts/static/yaccounts/libs/bootstrap-3.0.3/fonts/glyphicons-halflings-regular.ttf
yaccounts/static/yaccounts/libs/bootstrap-3.0.3/fonts/glyphicons-halflings-regular.woff
yaccounts/static/yaccounts/libs/bootstrap-3.0.3/js/bootstrap.js
yaccounts/static/yaccounts/libs/bootstrap-3.0.3/js/bootstrap.min.js
yaccounts/static/yaccounts/libs/font-awesome-4.0.3/.DS_Store
yaccounts/static/yaccounts/libs/font-awesome-4.0.3/css/font-awesome.css
yaccounts/static/yaccounts/libs/font-awesome-4.0.3/css/font-awesome.min.css
